windowstoast/__init__.py
windowstoast-0.0.4.dist-info/LICENSE
windowstoast-0.0.4.dist-info/METADATA
windowstoast-0.0.4.dist-info/WHEEL
windowstoast-0.0.4.dist-info/top_level.txt
windowstoast-0.0.4.dist-info/RECORD
