Metadata-Version: 2.1
Name: windowstoast
Version: 0.0.4
Summary: Toast notifications for Windows 11
Home-page: https://github.com/StealtherThreat/windowstoast
Author: Tushar Goyal
Author-email: StealtherThreat@outlook.com
Classifier: Programming Language :: Python :: 3
Classifier: License :: OSI Approved :: MIT License
Classifier: Operating System :: Microsoft :: Windows :: Windows 10
Requires-Python: >=3.6
License-File: LICENSE
